pysetns
