Metadata-Version: 2.1
Name: pysetns
Version: 0.2.1
Summary: Python wrapper for setns Linux syscall.
Home-page: https://github.com/baskiton/pysetns
Author: Alexander Baskikh
Author-email: baskiton@gmail.com
License: MIT
Project-URL: Source, https://github.com/baskiton/pysetns
Project-URL: Bug Tracker, https://github.com/baskiton/pysetns/issues
Keywords: linux kernel namespace setns
Platform: UNKNOWN
Classifier: License :: OSI Approved :: MIT License
Classifier: Programming Language :: Python :: 3
Classifier: Operating System :: POSIX :: Linux
Classifier: Topic :: System :: Operating System Kernels :: Linux
Requires-Python: >=3.6
License-File: LICENSE
